starrocks/__init__.py
starrocks/datatype.py
starrocks/dialect.py
starrocks/reflection.py
starrocks/requirements.py
starrocks/alembic/__init__.py
starrocks/alembic/compare.py
starrocks/alembic/ops.py
starrocks/alembic/render.py
starrocks/alembic/starrocks.py
starrocks/alembic/toimpl.py
starrocks/common/__init__.py
starrocks/common/consts.py
starrocks/common/defaults.py
starrocks/common/params.py
starrocks/common/types.py
starrocks/common/utils.py
starrocks/drivers/__init__.py
starrocks/drivers/grammar.lark
starrocks/drivers/parsers.py
starrocks/engine/__init__.py
starrocks/engine/interfaces.py
starrocks/sql/__init__.py
starrocks/sql/ddl.py
starrocks/sql/schema.py
starrocks-1.3.0.dist-info/LICENSE
starrocks-1.3.0.dist-info/METADATA
starrocks-1.3.0.dist-info/WHEEL
starrocks-1.3.0.dist-info/entry_points.txt
starrocks-1.3.0.dist-info/top_level.txt
starrocks-1.3.0.dist-info/RECORD
