Metadata-Version: 2.1
Name: starrocks
Version: 1.3.0
Summary: Python SQLAlchemy Dialect and Alembic integration for StarRocks
Home-page: https://github.com/StarRocks/starrocks
Author: StarRocks Team
License: Apache 2.0
Classifier: Development Status :: 5 - Production/Stable
Classifier: Environment :: Console
Classifier: Intended Audience :: Developers
Classifier: License :: OSI Approved :: Apache Software License
Classifier: Programming Language :: Python
Classifier: Programming Language :: Python :: 3 :: Only
Classifier: Programming Language :: Python :: 3.8
Classifier: Programming Language :: Python :: 3.9
Classifier: Programming Language :: Python :: 3.10
Classifier: Programming Language :: Python :: 3.11
Classifier: Programming Language :: Python :: 3.12
Classifier: Programming Language :: Python :: Implementation :: CPython
Classifier: Programming Language :: Python :: Implementation :: PyPy
Classifier: Topic :: Database :: Front-Ends
License-File: LICENSE
Requires-Dist: sqlalchemy>=1.4
Requires-Dist: sqlalchemy-utils>=0.41.2
Requires-Dist: pymysql>=1.1.0
Requires-Dist: alembic>=1.4.0
Requires-Dist: lark-parser>=0.12.0
